README.md
setup.py
Bert_clear_title/__init__.py
Bert_clear_title/marker.py
Bert_clear_title.egg-info/PKG-INFO
Bert_clear_title.egg-info/SOURCES.txt
Bert_clear_title.egg-info/dependency_links.txt
Bert_clear_title.egg-info/requires.txt
Bert_clear_title.egg-info/top_level.txt
test/test.py