Metadata-Version: 2.1
Name: Bert-clear-title
Version: 0.0.0.1.1
Summary: Terry toolkit Bert_clear_title
Home-page: http://terrychan.org/Bert_clear_title/
Author: Terry Chan
Author-email: napoler2008@gmail.com
License: UNKNOWN
Platform: UNKNOWN
